{
  "gitSyncId": "66fc47e97369a379b0eb904b_048222f3-33ea-46fd-aacd-716defde885a",
  "id": "LoginPage_UserSignIn.refreshAccessToken",
  "pluginId": "js-plugin",
  "pluginType": "JS",
  "unpublishedAction": {
    "actionConfiguration": {
      "encodeParamsToggle": true,
      "jsArguments": [],
      "paginationType": "NONE",
      "timeoutInMillisecond": 10000
    },
    "collectionId": "LoginPage_UserSignIn",
    "confirmBeforeExecute": false,
    "datasource": {
      "isAutoGenerated": false,
      "name": "UNUSED_DATASOURCE",
      "pluginId": "js-plugin"
    },
    "dynamicBindingPathList": [
      {
        "key": "body"
      }
    ],
    "executeOnLoad": false,
    "fullyQualifiedName": "UserSignIn.refreshAccessToken",
    "name": "refreshAccessToken",
    "pageId": "LoginPage",
    "userSetOnLoad": false
  }
}